validatezw/__init__.py
validatezw/validate.py
validatezw-0.0.1.dist-info/METADATA
validatezw-0.0.1.dist-info/WHEEL
validatezw-0.0.1.dist-info/top_level.txt
validatezw-0.0.1.dist-info/RECORD
